odoo8_addon_pos_payment_entries_globalization-8.0.1.0.0-py2.7-nspkg.pth
odoo8_addon_pos_payment_entries_globalization-8.0.1.0.0.dist-info/DESCRIPTION.rst
odoo8_addon_pos_payment_entries_globalization-8.0.1.0.0.dist-info/METADATA
odoo8_addon_pos_payment_entries_globalization-8.0.1.0.0.dist-info/RECORD
odoo8_addon_pos_payment_entries_globalization-8.0.1.0.0.dist-info/WHEEL
odoo8_addon_pos_payment_entries_globalization-8.0.1.0.0.dist-info/metadata.json
odoo8_addon_pos_payment_entries_globalization-8.0.1.0.0.dist-info/namespace_packages.txt
odoo8_addon_pos_payment_entries_globalization-8.0.1.0.0.dist-info/top_level.txt
odoo_addons/pos_payment_entries_globalization/README.rst
odoo_addons/pos_payment_entries_globalization/__init__.py
odoo_addons/pos_payment_entries_globalization/__openerp__.py
odoo_addons/pos_payment_entries_globalization/models/__init__.py
odoo_addons/pos_payment_entries_globalization/models/account_journal.py
odoo_addons/pos_payment_entries_globalization/models/pos_session.py
odoo_addons/pos_payment_entries_globalization/static/description/icon.png
odoo_addons/pos_payment_entries_globalization/tests/__init__.py
odoo_addons/pos_payment_entries_globalization/tests/test_pos_payment_entries_globalization.py
odoo_addons/pos_payment_entries_globalization/views/account_journal_view.xml
